jgreenepack/__init__.py
jgreenepack/api_client.py
jgreenepack/configuration.py
jgreenepack/rest.py
jgreenepack/api/__init__.py
jgreenepack/api/pets_api.py
jgreenepack/models/__init__.py
jgreenepack/models/error.py
jgreenepack/models/pet.py
jgreenepack/models/pets.py
test/__init__.py
test/test_error.py
test/test_pet.py
test/test_pets.py
test/test_pets_api.py
jgreenepack-1.79.0.dist-info/METADATA
jgreenepack-1.79.0.dist-info/WHEEL
jgreenepack-1.79.0.dist-info/top_level.txt
jgreenepack-1.79.0.dist-info/RECORD
