Metadata-Version: 2.1
Name: jgreenepack
Version: 1.79.0
Summary: Swagger Petstore
Home-page: UNKNOWN
Author-email: 
License: UNKNOWN
Keywords: Swagger,Swagger Petstore
Platform: UNKNOWN
Requires-Dist: certifi (>=2017.4.17)
Requires-Dist: python-dateutil (>=2.1)
Requires-Dist: six (>=1.10)
Requires-Dist: urllib3 (>=1.23)
